pybloomer.cp311-win_amd64.pyd
win/getopt.c
win/getopt.h
win/io_win.c
win/io_win.h
win/mman.c
win/mman.h
win/unistd.h
pybloomer-0.6.0.dist-info/AUTHORS
pybloomer-0.6.0.dist-info/LICENSE
pybloomer-0.6.0.dist-info/METADATA
pybloomer-0.6.0.dist-info/WHEEL
pybloomer-0.6.0.dist-info/top_level.txt
pybloomer-0.6.0.dist-info/RECORD
