Metadata-Version: 2.1
Name: pybloomer
Version: 0.6.0
Summary: A fast implementation of Bloom filter for Python built on mmap
Home-page: https://github.com/masroore/pybloomer
Author: Dr. Masroor Ehsan
Author-email: masroore+pypi@gmail.com
License: MIT License
Classifier: Development Status :: 4 - Beta
Classifier: Intended Audience :: Developers
Classifier: Intended Audience :: Science/Research
Classifier: License :: OSI Approved :: MIT License
Classifier: Programming Language :: C
Classifier: Programming Language :: Cython
Classifier: Programming Language :: Python
Classifier: Programming Language :: Python :: 3
Classifier: Programming Language :: Python :: 3.8
Classifier: Programming Language :: Python :: 3.9
Classifier: Programming Language :: Python :: 3.10
Classifier: Programming Language :: Python :: 3.11
Classifier: Programming Language :: Python :: 3.12
Classifier: Topic :: Software Development :: Libraries :: Python Modules
Requires-Python: >=3.8, <4
License-File: LICENSE
License-File: AUTHORS
